[ {
  "id" : "2_q7K1ioojiOV-iL1ayEQ",
  "salon" : "Lilla Salongen",
  "film" : "Pulp Fiction",
  "date" : "2021-02-19",
  "time" : "20:02",
  "showId" : "1",
  "availableSeats" : 56
}, {
  "id" : "chyuAFdSgXF0Eaima97Oz",
  "salon" : "Lilla Salongen",
  "film" : "Dansar Med Vargar",
  "date" : "2021-02-22",
  "time" : "18:59",
  "showId" : "2",
  "availableSeats" : 56
}, {
  "id" : "mj5CRTaL9PA2eKgp6MDwl",
  "salon" : "Lilla Salongen",
  "film" : "Pulp Fiction",
  "date" : "2021-02-17",
  "time" : "19:46",
  "showId" : "3",
  "availableSeats" : 56
}, {
  "id" : "Wkugpd8-FzBMVbfIClq9Q",
  "salon" : "Stora Salongen",
  "film" : "Blade Runner",
  "date" : "2021-02-12",
  "time" : "20:39",
  "showId" : "4",
  "availableSeats" : 81
}, {
  "id" : "fhi4pK6kWv_CPE7DBS2Lb",
  "salon" : "Lilla Salongen",
  "film" : "Borat 2",
  "date" : "2021-02-10",
  "time" : "21:44",
  "showId" : "5",
  "availableSeats" : 56
}, {
  "id" : "dkEQHo0LFiJkG04eF-na1",
  "salon" : "Stora Salongen",
  "film" : "Borat 2",
  "date" : "2021-02-04",
  "time" : "20:31",
  "showId" : "6",
  "availableSeats" : 81
}, {
  "id" : "Pz-gVOJpZ29AsFiome3hM",
  "salon" : "Lilla Salongen",
  "film" : "Blade Runner",
  "date" : "2021-02-03",
  "time" : "20:23",
  "showId" : "7",
  "availableSeats" : 56
}, {
  "id" : "QnX8UjL0e2NLtJd7k0fo_",
  "salon" : "Stora Salongen",
  "film" : "Star Wars: Episode III",
  "date" : "2021-02-02",
  "time" : "21:20",
  "showId" : "8",
  "availableSeats" : 81
}, {
  "id" : "fSZcEpYogIQq12XfIZM99",
  "salon" : "Stora Salongen",
  "film" : "Borat 2",
  "date" : "2021-02-03",
  "time" : "21:22",
  "showId" : "9",
  "availableSeats" : 81
}, {
  "id" : "_PTbCEWZtTbSPUEaKz2mp",
  "salon" : "Lilla Salongen",
  "film" : "Star Wars: Episode III",
  "date" : "2021-02-04",
  "time" : "20:02",
  "showId" : "10",
  "availableSeats" : 56
}, {
  "id" : "MDrh2G77_pvrgFhPPmFC4",
  "salon" : "Stora Salongen",
  "film" : "Pulp Fiction",
  "date" : "2021-02-15",
  "time" : "19:48",
  "showId" : "11",
  "availableSeats" : 81
}, {
  "id" : "v51fWk3rGqDmElNXfp7ED",
  "salon" : "Stora Salongen",
  "film" : "Dansar Med Vargar",
  "date" : "2021-02-07",
  "time" : "20:20",
  "showId" : "12",
  "availableSeats" : 81
}, {
  "id" : "B4zwGWYg2S4bWZnTmOaeo",
  "salon" : "Lilla Salongen",
  "film" : "Star Wars: Episode III",
  "date" : "2021-02-21",
  "time" : "19:44",
  "showId" : "13",
  "availableSeats" : 56
}, {
  "id" : "ArjM3Gl5Mu0I_M8QSzFWv",
  "salon" : "Lilla Salongen",
  "film" : "Dansar Med Vargar",
  "date" : "2021-02-11",
  "time" : "21:16",
  "showId" : "14",
  "availableSeats" : 56
}, {
  "id" : "QHdvEATrhr_x9w8bUJOVm",
  "salon" : "Lilla Salongen",
  "film" : "Star Wars: Episode III",
  "date" : "2021-02-16",
  "time" : "19:08",
  "showId" : "15",
  "availableSeats" : 56
}, {
  "id" : "BqfsRh_610CQjDhQt9jsM",
  "salon" : "Lilla Salongen",
  "film" : "Pulp Fiction",
  "date" : "2021-02-17",
  "time" : "19:07",
  "showId" : "16",
  "availableSeats" : 56
}, {
  "id" : "3FsX8KyTD0lzPcfXYx1RZ",
  "salon" : "Stora Salongen",
  "film" : "Dansar Med Vargar",
  "date" : "2021-02-27",
  "time" : "18:23",
  "showId" : "17",
  "availableSeats" : 81
}, {
  "id" : "VX8I028jWXK6li_lGWI_F",
  "salon" : "Stora Salongen",
  "film" : "Pulp Fiction",
  "date" : "2021-02-07",
  "time" : "20:47",
  "showId" : "18",
  "availableSeats" : 81
}, {
  "id" : "CTlzadJzBNnA9pbWdSrrT",
  "salon" : "Stora Salongen",
  "film" : "Pulp Fiction",
  "date" : "2021-02-16",
  "time" : "21:55",
  "showId" : "19",
  "availableSeats" : 81
}, {
  "id" : "ecw6WBa7iEZMYQh0jRYZh",
  "salon" : "Stora Salongen",
  "film" : "Pulp Fiction",
  "date" : "2021-02-04",
  "time" : "19:08",
  "showId" : "20",
  "availableSeats" : 81
}, {
  "id" : "BCdG5O2752xT5unsyp7ZL",
  "salon" : "Lilla Salongen",
  "film" : "Blade Runner",
  "date" : "2021-02-05",
  "time" : "18:50",
  "showId" : "21",
  "availableSeats" : 56
}, {
  "id" : "DUwrXUnEj4OQhYDNhBSv-",
  "salon" : "Lilla Salongen",
  "film" : "Borat 2",
  "date" : "2021-02-15",
  "time" : "18:19",
  "showId" : "22",
  "availableSeats" : 56
}, {
  "id" : "JWNJmQMjid8zD8UiPBIld",
  "salon" : "Lilla Salongen",
  "film" : "Pulp Fiction",
  "date" : "2021-02-11",
  "time" : "19:56",
  "showId" : "23",
  "availableSeats" : 56
}, {
  "id" : "wVecN-TX1XrguruZqwpLk",
  "salon" : "Stora Salongen",
  "film" : "Blade Runner",
  "date" : "2021-02-27",
  "time" : "21:02",
  "showId" : "24",
  "availableSeats" : 81
}, {
  "id" : "RVXg04QiSmOdzsf6NoNjg",
  "salon" : "Lilla Salongen",
  "film" : "Star Wars: Episode III",
  "date" : "2021-02-03",
  "time" : "18:32",
  "showId" : "25",
  "availableSeats" : 56
}, {
  "id" : "O6LJb7lbuGFNlzXVxa5vD",
  "salon" : "Stora Salongen",
  "film" : "Pulp Fiction",
  "date" : "2021-02-18",
  "time" : "18:11",
  "showId" : "26",
  "availableSeats" : 81
}, {
  "id" : "pxyu6fFc5l-FS5GvU43nV",
  "salon" : "Stora Salongen",
  "film" : "Pulp Fiction",
  "date" : "2021-02-13",
  "time" : "19:46",
  "showId" : "27",
  "availableSeats" : 81
}, {
  "id" : "cUnIhHQta-8ID_xV4C7Tj",
  "salon" : "Lilla Salongen",
  "film" : "Star Wars: Episode III",
  "date" : "2021-02-16",
  "time" : "19:06",
  "showId" : "28",
  "availableSeats" : 56
}, {
  "id" : "iznZ4ucdDZjiFihLhz3GP",
  "salon" : "Lilla Salongen",
  "film" : "Blade Runner",
  "date" : "2021-02-11",
  "time" : "18:37",
  "showId" : "29",
  "availableSeats" : 56
}, {
  "id" : "WvJuJi7rphWuP_RBIhg_x",
  "salon" : "Lilla Salongen",
  "film" : "Star Wars: Episode III",
  "date" : "2021-02-08",
  "time" : "18:47",
  "showId" : "30",
  "availableSeats" : 56
}, {
  "id" : "-UyDzRDJGO_8BMcrDazEi",
  "salon" : "Stora Salongen",
  "film" : "Borat 2",
  "date" : "2021-02-15",
  "time" : "19:47",
  "showId" : "31",
  "availableSeats" : 81
}, {
  "id" : "Pj5A2qGgvcKeW-vpz3BYh",
  "salon" : "Lilla Salongen",
  "film" : "Dansar Med Vargar",
  "date" : "2021-02-27",
  "time" : "21:47",
  "showId" : "32",
  "availableSeats" : 56
}, {
  "id" : "jU7iNF0N57bkYfjJsJv4t",
  "salon" : "Stora Salongen",
  "film" : "Borat 2",
  "date" : "2021-02-09",
  "time" : "21:15",
  "showId" : "33",
  "availableSeats" : 81
}, {
  "id" : "YctJldxhnilJsOjq-c-zS",
  "salon" : "Stora Salongen",
  "film" : "Dansar Med Vargar",
  "date" : "2021-02-21",
  "time" : "19:39",
  "showId" : "34",
  "availableSeats" : 81
}, {
  "id" : "6S3jm-jPy14DopqCpKvb8",
  "salon" : "Lilla Salongen",
  "film" : "Dansar Med Vargar",
  "date" : "2021-02-21",
  "time" : "20:56",
  "showId" : "35",
  "availableSeats" : 56
}, {
  "id" : "2u9fdr-x8QdviOI8uwSR1",
  "salon" : "Lilla Salongen",
  "film" : "Pulp Fiction",
  "date" : "2021-02-14",
  "time" : "20:10",
  "showId" : "36",
  "availableSeats" : 56
}, {
  "id" : "miVeJhIRFOJ9E5OWDt97H",
  "salon" : "Stora Salongen",
  "film" : "Blade Runner",
  "date" : "2021-02-23",
  "time" : "18:28",
  "showId" : "37",
  "availableSeats" : 81
}, {
  "id" : "rDQsH2GpW7g8jPZK-ccW8",
  "salon" : "Lilla Salongen",
  "film" : "Blade Runner",
  "date" : "2021-02-22",
  "time" : "18:09",
  "showId" : "38",
  "availableSeats" : 56
}, {
  "id" : "DLmMuQ_Vpu3LgtuA64POP",
  "salon" : "Lilla Salongen",
  "film" : "Borat 2",
  "date" : "2021-02-25",
  "time" : "19:08",
  "showId" : "39",
  "availableSeats" : 56
}, {
  "id" : "ubTAPRT6pGdm0hynus3YW",
  "salon" : "Lilla Salongen",
  "film" : "Borat 2",
  "date" : "2021-02-17",
  "time" : "18:09",
  "showId" : "40",
  "availableSeats" : 56
}, {
  "id" : "GnU0wQ-h9hTUXBcofbqj1",
  "salon" : "Stora Salongen",
  "film" : "Borat 2",
  "date" : "2021-02-20",
  "time" : "19:57",
  "showId" : "41",
  "availableSeats" : 81
}, {
  "id" : "cu3FEwbHfhlVoGSPUsjB6",
  "salon" : "Stora Salongen",
  "film" : "Star Wars: Episode III",
  "date" : "2021-02-24",
  "time" : "20:48",
  "showId" : "42",
  "availableSeats" : 81
}, {
  "id" : "wVKw7dkjEd7qFHP-yZdOR",
  "salon" : "Stora Salongen",
  "film" : "Dansar Med Vargar",
  "date" : "2021-02-02",
  "time" : "20:46",
  "showId" : "43",
  "availableSeats" : 81
}, {
  "id" : "DVxT1nhMrPn6TsVPa7Bp_",
  "salon" : "Lilla Salongen",
  "film" : "Blade Runner",
  "date" : "2021-02-19",
  "time" : "18:15",
  "showId" : "44",
  "availableSeats" : 56
}, {
  "id" : "93KEx9KC5hDXN-rQB4f0Q",
  "salon" : "Stora Salongen",
  "film" : "Dansar Med Vargar",
  "date" : "2021-02-15",
  "time" : "21:54",
  "showId" : "45",
  "availableSeats" : 81
}, {
  "id" : "h9BE3TUbk8n2PhLLoyDee",
  "salon" : "Stora Salongen",
  "film" : "Star Wars: Episode III",
  "date" : "2021-02-15",
  "time" : "21:42",
  "showId" : "46",
  "availableSeats" : 81
}, {
  "id" : "qcEUUjg03GD8xZoyURrRJ",
  "salon" : "Stora Salongen",
  "film" : "Star Wars: Episode III",
  "date" : "2021-02-18",
  "time" : "20:42",
  "showId" : "47",
  "availableSeats" : 81
}, {
  "id" : "nC0Hr9UP6gJWVyHlM-KtN",
  "salon" : "Lilla Salongen",
  "film" : "Borat 2",
  "date" : "2021-02-20",
  "time" : "20:52",
  "showId" : "48",
  "availableSeats" : 56
}, {
  "id" : "KLJGELV_f7I5ZN3w8quEz",
  "salon" : "Stora Salongen",
  "film" : "Blade Runner",
  "date" : "2021-02-11",
  "time" : "20:39",
  "showId" : "49",
  "availableSeats" : 81
}, {
  "id" : "yn-INTN4LaRq0skq-H9kH",
  "salon" : "Stora Salongen",
  "film" : "Star Wars: Episode III",
  "date" : "2021-02-18",
  "time" : "21:58",
  "showId" : "50",
  "availableSeats" : 81
}, {
  "id" : "-z3w8x-ZHbNSWKzc3V1dE",
  "salon" : "Stora Salongen",
  "film" : "Dansar Med Vargar",
  "date" : "2021-02-22",
  "time" : "21:33",
  "showId" : "51",
  "availableSeats" : 81
}, {
  "id" : "jSxSPW1uWUETZVMZDMVKA",
  "salon" : "Lilla Salongen",
  "film" : "Dansar Med Vargar",
  "date" : "2021-02-25",
  "time" : "20:51",
  "showId" : "52",
  "availableSeats" : 56
}, {
  "id" : "2tSaQoQOn0dWOAMpqtSIi",
  "salon" : "Lilla Salongen",
  "film" : "Borat 2",
  "date" : "2021-02-23",
  "time" : "21:01",
  "showId" : "53",
  "availableSeats" : 56
}, {
  "id" : "x2FH57-Mw5VMGpREv_h_h",
  "salon" : "Stora Salongen",
  "film" : "Dansar Med Vargar",
  "date" : "2021-02-23",
  "time" : "20:41",
  "showId" : "54",
  "availableSeats" : 81
}, {
  "id" : "GDVIycq7ABIwhJ5nx1Baz",
  "salon" : "Lilla Salongen",
  "film" : "Star Wars: Episode III",
  "date" : "2021-02-06",
  "time" : "18:26",
  "showId" : "55",
  "availableSeats" : 56
}, {
  "id" : "fSUfFloWXnvbX4AETfrrz",
  "salon" : "Lilla Salongen",
  "film" : "Star Wars: Episode III",
  "date" : "2021-02-19",
  "time" : "19:52",
  "showId" : "56",
  "availableSeats" : 56
}, {
  "id" : "1xCs_bUyHiPnUhwJaPe8Y",
  "salon" : "Lilla Salongen",
  "film" : "Borat 2",
  "date" : "2021-02-24",
  "time" : "20:27",
  "showId" : "57",
  "availableSeats" : 56
}, {
  "id" : "Af1xr8XofqHX0-ixVB5Wk",
  "salon" : "Stora Salongen",
  "film" : "Star Wars: Episode III",
  "date" : "2021-02-04",
  "time" : "19:36",
  "showId" : "58",
  "availableSeats" : 81
}, {
  "id" : "ZVrgYyXk7vwOM_FdqewUq",
  "salon" : "Lilla Salongen",
  "film" : "Borat 2",
  "date" : "2021-02-23",
  "time" : "21:55",
  "showId" : "59",
  "availableSeats" : 56
}, {
  "id" : "xqwoICWaR4Se6srs60DdG",
  "salon" : "Stora Salongen",
  "film" : "Blade Runner",
  "date" : "2021-02-11",
  "time" : "19:09",
  "showId" : "60",
  "availableSeats" : 81
}, {
  "id" : "GlMgsf0utMCO3Nfwyq9nI",
  "salon" : "Lilla Salongen",
  "film" : "Pulp Fiction",
  "date" : "2021-02-05",
  "time" : "21:14",
  "showId" : "61",
  "availableSeats" : 56
}, {
  "id" : "7Nlh76tQCfBF4S9PlCjRT",
  "salon" : "Stora Salongen",
  "film" : "Blade Runner",
  "date" : "2021-02-03",
  "time" : "20:32",
  "showId" : "62",
  "availableSeats" : 81
}, {
  "id" : "14payAnFz2NB3TmeW25N2",
  "salon" : "Stora Salongen",
  "film" : "Star Wars: Episode III",
  "date" : "2021-02-04",
  "time" : "18:20",
  "showId" : "63",
  "availableSeats" : 81
}, {
  "id" : "wCVP2F8HTR5O6qz1fJawg",
  "salon" : "Stora Salongen",
  "film" : "Pulp Fiction",
  "date" : "2021-02-05",
  "time" : "20:15",
  "showId" : "64",
  "availableSeats" : 81
}, {
  "id" : "V9z2t21OQ3qrwRiyZYNm-",
  "salon" : "Stora Salongen",
  "film" : "Pulp Fiction",
  "date" : "2021-02-02",
  "time" : "18:19",
  "showId" : "65",
  "availableSeats" : 81
}, {
  "id" : "_e4ASj2-hShu_EcMZOOtO",
  "salon" : "Stora Salongen",
  "film" : "Blade Runner",
  "date" : "2021-02-05",
  "time" : "21:59",
  "showId" : "66",
  "availableSeats" : 81
}, {
  "id" : "oaHywkDxUkPS72zdiU6Rd",
  "salon" : "Stora Salongen",
  "film" : "Blade Runner",
  "date" : "2021-02-07",
  "time" : "21:41",
  "showId" : "67",
  "availableSeats" : 81
}, {
  "id" : "PhEqwuQn0PXtmWqYHVVtU",
  "salon" : "Lilla Salongen",
  "film" : "Blade Runner",
  "date" : "2021-02-20",
  "time" : "20:23",
  "showId" : "68",
  "availableSeats" : 56
}, {
  "id" : "ly8lmMKIBDO3DHIEn7vOK",
  "salon" : "Stora Salongen",
  "film" : "Blade Runner",
  "date" : "2021-02-11",
  "time" : "18:45",
  "showId" : "69",
  "availableSeats" : 81
}, {
  "id" : "FnbQAV9Bnx5kNdmftLSQI",
  "salon" : "Stora Salongen",
  "film" : "Borat 2",
  "date" : "2021-02-14",
  "time" : "19:27",
  "showId" : "70",
  "availableSeats" : 81
}, {
  "id" : "0r3WZsqG-YI5-3Ir56RTS",
  "salon" : "Stora Salongen",
  "film" : "Blade Runner",
  "date" : "2021-02-23",
  "time" : "21:13",
  "showId" : "71",
  "availableSeats" : 81
}, {
  "id" : "mXcNKR5g9uHUb-kxN8qoe",
  "salon" : "Stora Salongen",
  "film" : "Star Wars: Episode III",
  "date" : "2021-02-02",
  "time" : "20:41",
  "showId" : "72",
  "availableSeats" : 81
}, {
  "id" : "IIHEL2mpW7X2GrvZiBa3P",
  "salon" : "Lilla Salongen",
  "film" : "Pulp Fiction",
  "date" : "2021-02-16",
  "time" : "20:50",
  "showId" : "73",
  "availableSeats" : 56
}, {
  "id" : "4LqK_rfgz2lbEzmhFGyIQ",
  "salon" : "Stora Salongen",
  "film" : "Pulp Fiction",
  "date" : "2021-02-13",
  "time" : "18:38",
  "showId" : "74",
  "availableSeats" : 81
}, {
  "id" : "slsKg0cJbXw_WXDndrx1E",
  "salon" : "Stora Salongen",
  "film" : "Blade Runner",
  "date" : "2021-02-03",
  "time" : "18:36",
  "showId" : "75",
  "availableSeats" : 81
}, {
  "id" : "KJ1DIZBrDQCGDAxF0ny6B",
  "salon" : "Stora Salongen",
  "film" : "Blade Runner",
  "date" : "2021-02-27",
  "time" : "20:19",
  "showId" : "76",
  "availableSeats" : 81
}, {
  "id" : "Dcz2c75y01nX_bExQi3Rd",
  "salon" : "Stora Salongen",
  "film" : "Blade Runner",
  "date" : "2021-02-22",
  "time" : "18:21",
  "showId" : "77",
  "availableSeats" : 81
}, {
  "id" : "GWfgzw2UXQbWbZrXoJkGk",
  "salon" : "Lilla Salongen",
  "film" : "Star Wars: Episode III",
  "date" : "2021-02-08",
  "time" : "20:02",
  "showId" : "78",
  "availableSeats" : 56
}, {
  "id" : "wp9PM5gOIiKRzamoiaACg",
  "salon" : "Lilla Salongen",
  "film" : "Borat 2",
  "date" : "2021-02-17",
  "time" : "21:07",
  "showId" : "79",
  "availableSeats" : 56
}, {
  "id" : "lNszOZnIatoaczgbrW4Fn",
  "salon" : "Lilla Salongen",
  "film" : "Star Wars: Episode III",
  "date" : "2021-02-10",
  "time" : "18:46",
  "showId" : "80",
  "availableSeats" : 56
}, {
  "id" : "yOHs2OJczJME9xitxYS7W",
  "salon" : "Lilla Salongen",
  "film" : "Blade Runner",
  "date" : "2021-02-04",
  "time" : "18:17",
  "showId" : "81",
  "availableSeats" : 56
}, {
  "id" : "bLo3FcZ-G2rT1FtfWUGMm",
  "salon" : "Stora Salongen",
  "film" : "Star Wars: Episode III",
  "date" : "2021-02-24",
  "time" : "21:06",
  "showId" : "82",
  "availableSeats" : 81
}, {
  "id" : "6VVJ51f5ki4vNIgDJA8w5",
  "salon" : "Stora Salongen",
  "film" : "Dansar Med Vargar",
  "date" : "2021-02-01",
  "time" : "21:09",
  "showId" : "83",
  "availableSeats" : 81
}, {
  "id" : "0hCC7vZSP5OiNqKporDiv",
  "salon" : "Stora Salongen",
  "film" : "Star Wars: Episode III",
  "date" : "2021-02-21",
  "time" : "19:20",
  "showId" : "84",
  "availableSeats" : 81
}, {
  "id" : "XsA6lxoqr-2ZUSe1JdRoK",
  "salon" : "Lilla Salongen",
  "film" : "Pulp Fiction",
  "date" : "2021-02-05",
  "time" : "21:05",
  "showId" : "85",
  "availableSeats" : 56
} ]